{"data":{"site":{"siteMetadata":{"author":{"name":"Danny Seymour","bio":"FullStack Developer.","photo":"/photo.jpeg","contacts":{"email":"#","telegram":"#","twitter":"https://twitter.com/Danny_SASeymour","github":"https://github.com/dsaseymour","rss":"#","vkontakte":"#"}},"menu":[{"label":"My Website","path":"/"},{"label":"Articles","path":"/blog/"},{"label":"About me","path":"/blog/pages/about"},{"label":"Contact me","path":"/blog/pages/contacts"}],"url":"https://lumen.netlify.com","title":"Professor Infosec","subtitle":"Painting the Big Picture without missing the details","copyright":"Danny Seymour © All rights reserved.","disqusShortname":""}}}}